{
  "mejia_haro": {
    "total": 12,
    "por_fecha": {
      "2026-03-14": 0,
      "2026-03-15": 1
    }
  },
  "saul_monreal": {
    "total": 13,
    "por_fecha": {
      "2026-03-14": 0,
      "2026-03-15": 1
    }
  },
  "diaz_robles": {
    "total": 12,
    "por_fecha": {
      "2026-03-14": 0,
      "2026-03-15": 1
    }
  },
  "narro_cespedes": {
    "total": 10,
    "por_fecha": {
      "2026-03-14": 0,
      "2026-03-15": 0
    }
  },
  "varela_pinedo": {
    "total": 10,
    "por_fecha": {
      "2026-03-14": 0,
      "2026-03-15": 0
    }
  },
  "bonilla_gomez": {
    "total": 10,
    "por_fecha": {
      "2026-03-14": 0,
      "2026-03-15": 1
    }
  },
  "anaya_mota": {
    "total": 10,
    "por_fecha": {
      "2026-03-14": 0,
      "2026-03-15": 1
    }
  }
}