{
  "version": "https://jsonfeed.org/version/1.1",
  "title": "Nicho Analyzer — Mineria Metales",
  "description": "Datos sobre Mineria Metales en Mexico y LATAM.",
  "home_page_url": "https://ruskigarage-alt.github.io/nicho-analyzer",
  "feed_url": "https://ruskigarage-alt.github.io/nicho-analyzer/feed/mineria_metales.json",
  "language": "es-MX",
  "date_modified": "2026-03-13T07:14:44.656952+00:00",
  "total_records": 12,
  "items": [
    {
      "id": "https://ruskigarage-alt.github.io/nicho-analyzer/feed/mineria_metales.json#0",
      "title": "Cobre — 2026-03-13",
      "content_text": "Cobre: USD 5.802 al 2026-03-13. Chile mayor productor mundial, Peru 2do.",
      "date_published": "2026-03-13T07:13:00.386269+00:00",
      "url": "https://finance.yahoo.com/quote/HG=F",
      "tags": [
        "mineria_metales",
        "Yahoo Finance — LME/CME"
      ]
    },
    {
      "id": "https://ruskigarage-alt.github.io/nicho-analyzer/feed/mineria_metales.json#1",
      "title": "Plata — 2026-03-13",
      "content_text": "Plata: USD 82.765 al 2026-03-13. Mexico mayor productor mundial.",
      "date_published": "2026-03-13T07:13:00.386269+00:00",
      "url": "https://finance.yahoo.com/quote/SI=F",
      "tags": [
        "mineria_metales",
        "Yahoo Finance — LME/CME"
      ]
    },
    {
      "id": "https://ruskigarage-alt.github.io/nicho-analyzer/feed/mineria_metales.json#2",
      "title": "Oro — 2026-03-13",
      "content_text": "Oro: USD 5092.4 al 2026-03-13. Mexico 9no productor mundial.",
      "date_published": "2026-03-13T07:13:00.386269+00:00",
      "url": "https://finance.yahoo.com/quote/GC=F",
      "tags": [
        "mineria_metales",
        "Yahoo Finance — LME/CME"
      ]
    },
    {
      "id": "https://ruskigarage-alt.github.io/nicho-analyzer/feed/mineria_metales.json#3",
      "title": "Aluminio — 2026-03-13",
      "content_text": "Aluminio: USD 3458.0 al 2026-03-13. insumo industria automotriz Mexico.",
      "date_published": "2026-03-13T07:13:00.386269+00:00",
      "url": "https://finance.yahoo.com/quote/ALI=F",
      "tags": [
        "mineria_metales",
        "Yahoo Finance — LME/CME"
      ]
    },
    {
      "id": "https://ruskigarage-alt.github.io/nicho-analyzer/feed/mineria_metales.json#4",
      "title": "Paladio — 2026-03-13",
      "content_text": "Paladio: USD 1626.0 al 2026-03-13. metales del grupo platino.",
      "date_published": "2026-03-13T07:13:00.386269+00:00",
      "url": "https://finance.yahoo.com/quote/PA=F",
      "tags": [
        "mineria_metales",
        "Yahoo Finance — LME/CME"
      ]
    },
    {
      "id": "https://ruskigarage-alt.github.io/nicho-analyzer/feed/mineria_metales.json#5",
      "title": "Platino — 2026-03-13",
      "content_text": "Platino: USD 2098.4 al 2026-03-13. tierras raras y metales criticos.",
      "date_published": "2026-03-13T07:13:00.386269+00:00",
      "url": "https://finance.yahoo.com/quote/PL=F",
      "tags": [
        "mineria_metales",
        "Yahoo Finance — LME/CME"
      ]
    },
    {
      "id": "https://ruskigarage-alt.github.io/nicho-analyzer/feed/mineria_metales.json#6",
      "title": "Zinc — 2026-03-13",
      "content_text": "Zinc: USD 111.45313 al 2026-03-13. Mexico top 5 productor mundial.",
      "date_published": "2026-03-13T07:13:00.386269+00:00",
      "url": "https://finance.yahoo.com/quote/ZN=F",
      "tags": [
        "mineria_metales",
        "Yahoo Finance — LME/CME"
      ]
    },
    {
      "id": "https://ruskigarage-alt.github.io/nicho-analyzer/feed/mineria_metales.json#7",
      "title": "Plomo — 2026-03-13",
      "content_text": "Plomo: USD 380.6 al 2026-03-13. Mexico productor relevante.",
      "date_published": "2026-03-13T07:13:00.386269+00:00",
      "url": "https://finance.yahoo.com/quote/LBS=F",
      "tags": [
        "mineria_metales",
        "Yahoo Finance — LME/CME"
      ]
    },
    {
      "id": "https://ruskigarage-alt.github.io/nicho-analyzer/feed/mineria_metales.json#8",
      "title": "Accion Albemarle (ALB) — 2026-03-13",
      "content_text": "Albemarle (ALB): USD 163.89 al 2026-03-13. mayor productor litio mundial, opera en Chile y Australia. Indicador de mercado de litio y tierras raras relevante para Mexico y LATAM.",
      "date_published": "2026-03-13T07:13:00.386269+00:00",
      "url": "https://finance.yahoo.com/quote/ALB",
      "tags": [
        "mineria_metales",
        "Yahoo Finance — Litio/Tierras raras"
      ]
    },
    {
      "id": "https://ruskigarage-alt.github.io/nicho-analyzer/feed/mineria_metales.json#9",
      "title": "Accion SQM (SQM) — 2026-03-13",
      "content_text": "SQM (SQM): USD 75.67 al 2026-03-13. productor litio Chile — Atacama. Indicador de mercado de litio y tierras raras relevante para Mexico y LATAM.",
      "date_published": "2026-03-13T07:13:00.386269+00:00",
      "url": "https://finance.yahoo.com/quote/SQM",
      "tags": [
        "mineria_metales",
        "Yahoo Finance — Litio/Tierras raras"
      ]
    },
    {
      "id": "https://ruskigarage-alt.github.io/nicho-analyzer/feed/mineria_metales.json#10",
      "title": "Accion Lithium Americas (LAC) — 2026-03-13",
      "content_text": "Lithium Americas (LAC): USD 4.55 al 2026-03-13. proyecto Thacker Pass y Caucharí-Olaroz Argentina. Indicador de mercado de litio y tierras raras relevante para Mexico y LATAM.",
      "date_published": "2026-03-13T07:13:00.386269+00:00",
      "url": "https://finance.yahoo.com/quote/LAC",
      "tags": [
        "mineria_metales",
        "Yahoo Finance — Litio/Tierras raras"
      ]
    },
    {
      "id": "https://ruskigarage-alt.github.io/nicho-analyzer/feed/mineria_metales.json#11",
      "title": "LME — precios metales industriales 2026-03-13",
      "content_text": "El London Metal Exchange publica precios oficiales de cobre, aluminio, zinc, plomo, estanio y niquel. Estos precios son referencia global para contratos de exportacion minera LATAM. Consulta: https://www.lme.com/en/metals. Fecha: 2026-03-13.",
      "date_published": "2026-03-13T07:13:00.386269+00:00",
      "url": "https://www.lme.com/en/metals",
      "tags": [
        "mineria_metales",
        "London Metal Exchange"
      ]
    }
  ]
}