{
  "id": "anaya_mota",
  "nombre": "Claudia Anaya Mota",
  "partido": "PRI",
  "partyClass": "pri",
  "actualizado": "2026-03-20",
  "fuente_wiki": "https://es.wikipedia.org/wiki/Claudia_Anaya_Mota",
  "bio_corta": "Claudia Edith Anaya Mota(Zacatecas,Zacatecas; 6 de junio de 1979) es Doctora en Administración Pública,[1]​ Maestra en Población, Desarrollo y Políticas Públicas,[1]​mercadólogaypolíticamexicana delPartido Revolucionario Institucional[2]​ que desde el 2018 se desempeña comoSenadora de la Repúblicapor el estado deZacatecasy fue reelecta para el cargo en 2024. De 2009 a 2012 fue diputada federal en la LXI Legislatura,[3]​ presidente de la Comisión Especial sobre la No Discriminación, secretaria de la Comisión de Hacienda y Crédito Público, integrante de las comisiones de Atención a Grupos Vulner",
  "nacimiento": "6 de junio de 1979 (46 años) Zacatecas , Zacatecas , México",
  "educacion": [
    "Mercadotecnia , población , desarrollo y políticas públicas"
  ],
  "partido_actual": "Partido Revolucionario Institucional (desde 2013) Partido de la Revolución Democ",
  "militancia_desde": "—",
  "cargo_actual": "Senadora de la República",
  "cargos": [],
  "vinculos": [],
  "cargos_detectados": [
    "En la LXV y LXVI Legistaturas del Senado de la República, se destacó como Secretaria de la Mesa Directiva, uno de los órganos legislativos más relevantes de esa Cámara. (7)",
    "Diputada federal (2009-2012)",
    "Diputada local (2013-2015)",
    "Diputada federal (2015-2018)"
  ]
}